org_model_documents/__init__.py
org_model_documents/admin.py
org_model_documents/api.py
org_model_documents/apps.py
org_model_documents/migrations/0001_initial.py
org_model_documents/migrations/0002_alter_document_unique_together.py
org_model_documents/migrations/__init__.py
org_model_documents/models.py
org_model_documents/serializers.py
org_model_documents/tests.py
org_model_documents/urls.py
org_model_documents/views.py
django_org_model_documents-1.0.0.dist-info/LICENSE
django_org_model_documents-1.0.0.dist-info/WHEEL
django_org_model_documents-1.0.0.dist-info/METADATA
django_org_model_documents-1.0.0.dist-info/RECORD
